  {
   "urls": [
    {"url": "https://raw.gitcode.com/frxz751113/1/raw/main/2.json", "name":"默认线路"},
    {"url": "https://raw.gitcode.com/frxz751113/1/raw/main/影视线路.json", "name":"影视线路"},
    {"url": "https://raw.gitcode.com/frxz751113/2/raw/master/%E6%95%99%E8%82%B2.json", "name":"知识百科"},
    {"url": "https://raw.gitcode.com/qq_33200661/12/raw/master/1.josn", "name":"你看你"},
    {"url": "https://gitee.com/ohday365/xijing/raw/master/xijing.bin","name":"曦静影视"},
    {"url": "https://pastebin.com/raw/5NHaxyGR", "name":"道长线路"},
    {"url": "http://home.jundie.top:81/top98.json", "name":"俊佬线路"},
    {"url": "https://raw.liucn.cc/box/m.json", "name":"老刘备线路"},
    {"url": "https://weixine.net/ysc.json", "name":"运输车线路"}
     //{"url": "https://weixine.net/ysc.json", "name":"运输车线路"}
]}
